vpp_ward/__init__.py
vpp_ward/apis.py
vpp_ward-0.1.0.dist-info/licenses/LICENSE
vpp_ward-0.1.0.dist-info/METADATA
vpp_ward-0.1.0.dist-info/WHEEL
vpp_ward-0.1.0.dist-info/top_level.txt
vpp_ward-0.1.0.dist-info/RECORD
