Metadata-Version: 2.4
Name: vpp_ward
Version: 0.1.0
Summary: Integration tools for integration tools for Virtual Power Plant modelling
Author-email: Peter McCallum <peter.mccallum@ed.ac.uk>
Requires-Python: >=3.10
License-File: LICENSE
Requires-Dist: openmeteo_requests==1.7.0
Requires-Dist: pandas==2.3.1
Requires-Dist: Requests==2.32.4
Requires-Dist: requests_cache==1.2.1
Requires-Dist: retry_requests==2.0.0
Dynamic: license-file
